testchr01/__init__.py
testchr01/hello.py
testchr01-0.1.0.dist-info/WHEEL
testchr01-0.1.0.dist-info/METADATA
testchr01-0.1.0.dist-info/RECORD
