Metadata-Version: 2.1
Name: testchr01
Version: 0.1.0
Summary: Chris Playground
Author: Christiano Anderson
Author-email: chris@christiano.dev
Requires-Python: >=3.8,<4.0
Classifier: Programming Language :: Python :: 3
Classifier: Programming Language :: Python :: 3.8
Requires-Dist: requests (>=2.23.0,<3.0.0)
